meta/__init__.py
meta/compat.py
meta/models.py
meta/settings.py
meta/utils.py
meta/views.py
meta/locale/ar/LC_MESSAGES/django.po
meta/locale/de/LC_MESSAGES/django.po
meta/locale/en/LC_MESSAGES/django.po
meta/locale/es/LC_MESSAGES/django.po
meta/locale/it/LC_MESSAGES/django.po
meta/locale/lt/LC_MESSAGES/django.po
meta/locale/nl/LC_MESSAGES/django.po
meta/locale/pt_BR/LC_MESSAGES/django.po
meta/locale/ru/LC_MESSAGES/django.po
meta/locale/tr/LC_MESSAGES/django.po
meta/locale/uz/LC_MESSAGES/django.po
meta/templates/meta.html
meta/templates/meta/meta.html
meta/templates/meta_mixin/meta.html
meta/templatetags/__init__.py
meta/templatetags/meta.py
meta/templatetags/meta_extra.py
django_meta-2.4.2.dist-info/LICENSE
django_meta-2.4.2.dist-info/METADATA
django_meta-2.4.2.dist-info/WHEEL
django_meta-2.4.2.dist-info/top_level.txt
django_meta-2.4.2.dist-info/RECORD
