Metadata-Version: 2.1
Name: django-meta
Version: 2.4.2
Summary: Pluggable app for handling webpage meta tags and OpenGraph properties
Home-page: https://github.com/nephila/django-meta
Author: Monwara LLC
Author-email: branko@monwara.com
Maintainer: Nephila
Maintainer-email: info@nephila.digital
License: BSD
Project-URL: Documentation, https://django-meta.readthedocs.io/
Classifier: Development Status :: 5 - Production/Stable
Classifier: Framework :: Django
Classifier: Framework :: Django :: 3.2
Classifier: Framework :: Django :: 4.0
Classifier: Framework :: Django :: 4.1
Classifier: Framework :: Django :: 4.2
Classifier: Environment :: Web Environment
Classifier: Intended Audience :: Developers
Classifier: License :: OSI Approved :: BSD License
Classifier: Programming Language :: Python :: 3
Classifier: Programming Language :: Python :: 3.9
Classifier: Programming Language :: Python :: 3.10
Classifier: Programming Language :: Python :: 3.11
Requires-Python: >=3.7
License-File: LICENSE
Provides-Extra: docs
Requires-Dist: django<5.0; extra == "docs"
Requires-Dist: sphinx-rtd-theme; extra == "docs"
